Metadata-Version: 2.1
Name: nmongo
Version: 0.6.0
Summary: Azure Cosmos DB for MongoDB client
Home-page: https://github.com/nakagami/nmongo/
Author: Hajime Nakagami
Author-email: nakagami@gmail.com
License: MIT
Keywords: MongoDB
Classifier: Development Status :: 4 - Beta
Classifier: License :: OSI Approved :: MIT License
Classifier: Operating System :: OS Independent
Classifier: Programming Language :: Python
Classifier: Programming Language :: Python :: 3
Classifier: Topic :: Database
License-File: LICENSE
